{"giaKeKhai":null,"nongDo":" 100 mg; 50 mg; 81,5 mg; 8,5 mg","hoatChat":"Cao khô lá tươi Actiso (tương đương với 2500 mg lá tươi actiso); Cao khô Diệp hạ châu (tương đương 400 mg Diệp hạ châu); Cao khô Rau đắng đất (tương đương với 500 mg Rau đắng đất); Cao khô Bìm bìm biếc (tương đương 85 mg Bìm bìm biếc) ","tuoiTho":"36 tháng","dongGoi":"Hộp 2 vỉ x 20 viên (vỉ nhôm - PVC); Hộp 1 chai 100 viên (chai nhựa HDPE)","tenThuoc":"Livonic","taDuoc":"Silicon dioxide dạng keo khan, lactose monohydrat, natri starch glycolat, tinh bột ngô, talc, magnesi stearat, Gôm arabic, Gelatin, Đường trắng, Titan dioxyd, sắt xyd đỏ, sắt oxyd đen, Màu amaranth, sáp carnauba, Ethanol 96%, nước tinh khiết vừa đủ","soLuong":0}