{"giaKeKhai":null,"nongDo":"330 mg; 330 mg; 330 mg; 330 mg; 330 mg; 330 mg; 330 mg; 330 mg; 330 mg; 60 mg; 60 mg; 60 mg; 60 mg; 30 mg","hoatChat":"Cao khô hỗn hợp dược liệu 390 mg (tương ứng với : Độc hoạt 330 mg; Phòng phong 330 mg; Tang ký sinh 330 mg; Tần giao 330 mg; Bạch thược 330 mg; Ngưu tất 330 mg; Sinh địa 330 mg; Cam thảo 330 mg; Đỗ trọng 330 mg; Tế tân 60 mg; Quế nhục 60 mg; Nhân sâm 60 mg; Dương quy 60 mg; Xuyên khung 30 mg","tuoiTho":"24 tháng","dongGoi":"Hộp 1 chai 40 viên; Hộp 10 vỉ x 10 viên","ID":37237,"tenThuoc":"V.phonte","taDuoc":null,"soLuong":0}