{"giaKeKhai":null,"nongDo":"30 mg","hoatChat":"Lansoprazol (dưới dạng vi hạt bao tan trong ruột) ","tuoiTho":"24 tháng","dongGoi":"Hộp 3 vỉ x 10 viên","ID":3897,"tenThuoc":"Artlanzo","taDuoc":"Mannitol,  Hydroxyl propyl  methyl  cellulose  (HPMC-E-5),  Methẩcrylic acid co-polymer,  natri  lauryl  sulphat,  Di natri hydrogen ortho phosphat,  Sucrose, Methyl paraben natri, Propyl paraben natri, Titan dioxid, Poly vinyl pyrrolidon K- 30, Calci carbonat, Talc, Diethyl phthalat, Polysorbat 80, Natri hydroxid, nang cứng gelatin số 2","soLuong":0}