{"giaKeKhai":null,"nongDo":"2,76g; 4,14g; 2,76g; 2,76g; 2,76g; 2,76g; 1,38g; 1,38g; 1,38g; 1,38g; 1,38g; 1,38g; 0,69g; 0,69g; 0,69g","hoatChat":"Mỗi chai 30g viên hoàn cứng chứa: Đảng sâm 2,76g; Địa hoàng 4,14g; Bạch thược 2,76g; Đỗ trọng 2,76g; Phục linh 2,76g; Đương quy 2,76g; Xuyên Khung 1,38g; Ngưu Tất  1,38g; Tang ký sinh 1,38g; Phòng phong 1,38g; Tần giao 1,38g; Độc hoạt 1,38g; Cam thảo 0,69g; Tế tân 0,69g; Quế 0,69g; ; ;","tuoiTho":"24 tháng","dongGoi":"Hộp 1 Chai 30 gam","ID":39701,"tenThuoc":"Phong thấp hoàn","taDuoc":null,"soLuong":0}