{"giaKeKhai":null,"nongDo":"140 mg; 200 mg; 25 mg; 50 mg; 25 mg","hoatChat":"Cao khô Carduus marianus (tương đương Silymarin toàn phần 70 mg) 140 mg; Cao khô diệp hạ châu (tương ứng với 1400 mg dược liệu) 200 mg; Cao khô ngũ vị tử (tương ứng với 150 mg dược liệu) 25 mg; Cao khô nhân trần (tương ứng với 714,5 mg dược liệu) 50 mg; Curcuminoids (Chiết xuất từ nghệ Curcuma longa L.) 25 mg","tuoiTho":"36 tháng","dongGoi":"Hộp 3 vỉ, 6 vỉ x 10 viên","ID":4974,"tenThuoc":"Silymax complex","taDuoc":null,"soLuong":0}