{"giaKeKhai":null,"nongDo":"0,095 mg; 0,01 mg; 0,05 mg; 60,8 mg; 60,0 mg","hoatChat":"Vitamin B9 (Acid folic); Vitamin B12 (Cyanocobalamin); Biotin; Ferrous fumarate; Acid ascorbic ","tuoiTho":"36 tháng","dongGoi":"Hộp 1 chai 30 viên","ID":8346,"tenThuoc":"Pedia Heam","taDuoc":"accharin natri, sucralose, glucose, hương liệu vanilla (Trusil nature identical vanillaflavour), hương liệu dâu tây (Trusll  natural strawberry flavour), fructose, sắt oxid, magnesistearat, acid stearic, silic dạng keo khan","soLuong":0}